.gitignore
.gitlab-ci.yml
README.md
environment.yml
pyproject.toml
requirements.txt
setup.cfg
setup.py
tox.ini
docs/Makefile
docs/conf.py
docs/index.rst
docs/make.bat
tcs_client/__init__.py
tcs_client/tcs_client.py
tcs_client.egg-info/PKG-INFO
tcs_client.egg-info/SOURCES.txt
tcs_client.egg-info/dependency_links.txt
tcs_client.egg-info/entry_points.txt
tcs_client.egg-info/not-zip-safe
tcs_client.egg-info/requires.txt
tcs_client.egg-info/top_level.txt
tcs_client/tests/__init__.py