Metadata-Version: 2.1
Name: tcs-client
Version: 1.0.0
Summary: Python Client for the Telescope Control System
Home-page: https://gitlab.com/nsf-noirlab/soar/py-tcs-client
Author: Diego Gomez, Simon Torres
Author-email: diego.gomez@noirlab.edu, simon.torres@noirlab.edu
License: BSD-3-Clause
Platform: UNKNOWN
Requires-Python: >=3.7
Provides-Extra: test
